{
    "lastRunAt":  "2026-04-04T10:37:13.4138134-07:00",
    "latestResult":  {
                         "title":  "Antigravity pod sweep complete",
                         "summary":  "Antigravity is actively cycling the conversion, search, and audit pods in bounded sequence with Gemma 4 as the first cheap utility lane.",
                         "suggestedHumanFix":  "No immediate human fix needed."
                     },
    "blocker":  "none",
    "currentTask":  {
                        "id":  "antigravity-conversion-creator-001",
                        "title":  "Sharpen the first creator-pilot economics and low-friction offer",
                        "kind":  "conversion-pod"
                    },
    "status":  "running",
    "lastSuccessAt":  "2026-04-04T10:37:13.4138134-07:00",
    "blockedUntil":  null,
    "nextEligibleRunAt":  null,
    "lastHeartbeatAt":  "2026-04-04T10:37:13.4138134-07:00",
    "staleAfterMinutes":  45,
    "semanticStatus":  "live",
    "nextCheckAt":  "2026-04-04T10:49:13.4138134-07:00",
    "lastPatrolFingerprint":  "antigravity-conversion-creator-001|Sharpen the first creator-pilot economics and low-friction offer|none",
    "handoffPacket":  {
                          "nextTaskId":  "antigravity-conversion-creator-001",
                          "doneWhen":  "The active pod produces a clean handoff or is replaced by a better-bounded pod.",
                          "handoffTo":  "manager",
                          "artifactPaths":  [
                                                "C:\\Users\\Chapman\\Desktop\\ai\\chapai\\config\\antigravity-queue.json",
                                                "C:\\Users\\Chapman\\Desktop\\ai\\chapai\\config\\antigravity-state.json",
                                                "C:\\Users\\Chapman\\Desktop\\ai\\chapai\\brains\\agents\\antigravity.json"
                                            ],
                          "resumeFrom":  "Resume from the active pod and keep it serialized.",
                          "wakeCondition":  "Wake on the next pod sweep or when the queue changes."
                      },
    "providerMode":  "gemma4-first bounded pod routing"
}