{
    "lane":  "content-engine",
    "startedAt":  "2026-04-04T09:21:01.8937170-07:00",
    "status":  "idle",
    "reason":  "batch fresh",
    "batchStatus":  {
                        "route":  "batch-status",
                        "ok":  true,
                        "output":  "Route: batch-status (ok)\r\nState: mixed-batch-516\r\nResult: 10 questions | CCRN 5 / NCLEX 5 | promoted\r\nBlocker: none\r\nNext: cmd:exec promote-staged-batches",
                        "ranAt":  "2026-04-04T09:21:02.1433242-07:00"
                    },
    "workerCycle":  null,
    "latestPromoted":  {
                           "file":  "mixed-batch-516.json",
                           "lastWriteTime":  "2026-04-04T09:19:59.8636207-07:00",
                           "ageMinutes":  1
                       },
    "lastUpdatedAt":  "2026-04-04T09:21:02.1778622-07:00"
}