{
    "generatedAt":  "2026-04-04T09:30:42.5820085-07:00",
    "batchId":  "mixed-batch-516",
    "promotedCount":  8,
    "ids":  [
                "mb516-n001",
                "mb516-n003",
                "mb516-n004",
                "mb516-n005",
                "mb516-c002",
                "mb516-c003",
                "mb516-c004",
                "mb516-c005"
            ],
    "byExam":  {
                   "ccrn":  {
                                "total":  581,
                                "added":  0,
                                "updated":  4
                            },
                   "nclex":  {
                                 "total":  542,
                                 "added":  0,
                                 "updated":  4
                             }
               }
}